CHANGES.md
MANIFEST.in
README.md
setup.py
meta_func/__init__.py
meta_func/meta_func.py
meta_func.egg-info/PKG-INFO
meta_func.egg-info/SOURCES.txt
meta_func.egg-info/dependency_links.txt
meta_func.egg-info/requires.txt
meta_func.egg-info/top_level.txt