Metadata-Version: 1.0
Name: meta-func
Version: 0.1.3
Summary: Python decorator function to track metadata on function calls
Home-page: http://www.github.com/gstaubli/meta_func
Author: Garren Staubli
Author-email: gstaubli@gmail.com
License: UNKNOWN
Platform: UNKNOWN
